[
  {
    "invocation" : ["otc-nonterminals-to-exemplars", "<INFILELIST>", "-o"],
    "infile_list": ["3genus-taxonomy.tre", "3genus-subsamplehigher.tre"],
    "expected": "expandunsampled"
  },
  {
    "invocation" : ["otc-nonterminals-to-exemplars", "<INFILELIST>", "-o"],
    "infile_list": ["3genus-taxonomy.tre", "3genus-subsamplehigher.tre", "3genus-complementhigher.tre"],
    "expected": "expandsampled"
  },
  {
    "invocation" : ["otc-nonterminals-to-exemplars", "<INFILELIST>", "-o"],
    "infile_list": ["3level-taxonomy.tre", "3level-subsamplehigher.tre", "3level-complementhigher.tre"],
    "expected": "expandnested"
  },
  {
    "invocation" : ["otc-nonterminals-to-exemplars", "<INFILELIST>", "-o"],
    "infile_list": ["3level-taxonomy.tre", "3level-subsamplehigher.tre", "3level-ACvB.tre"],
    "expected": "expandAC"
  }
]
